ubuntui/__init__.py
ubuntui/anchors.py
ubuntui/dialog.py
ubuntui/ev.py
ubuntui/frame.py
ubuntui/lists.py
ubuntui/palette.py
ubuntui/utils.py
ubuntui/views/__init__.py
ubuntui/views/error.py
ubuntui/views/infodialog.py
ubuntui/views/selectordialog.py
ubuntui/views/statusbar.py
ubuntui/widgets/__init__.py
ubuntui/widgets/buttons.py
ubuntui/widgets/dropdown.py
ubuntui/widgets/hr.py
ubuntui/widgets/input.py
ubuntui/widgets/lists.py
ubuntui/widgets/meta.py
ubuntui/widgets/table.py
ubuntui/widgets/text.py
ubuntui/widgets/juju/__init__.py
ubuntui/widgets/juju/machine.py
ubuntui/widgets/juju/service.py
ubuntui/widgets/juju/unit.py
ubuntui/widgets/maas/__init__.py
ubuntui/widgets/maas/machine.py
ubuntui-0.1.9.dist-info/DESCRIPTION.rst
ubuntui-0.1.9.dist-info/METADATA
ubuntui-0.1.9.dist-info/RECORD
ubuntui-0.1.9.dist-info/WHEEL
ubuntui-0.1.9.dist-info/metadata.json
ubuntui-0.1.9.dist-info/top_level.txt
