Metadata-Version: 2.0
Name: ubuntui
Version: 0.1.9
Summary: Urwid widgets used in Ubuntu console apps
Home-page: https://github.com/canonicalltd/urwid-ubuntu
Author: Canonical Solutions Engineering
Author-email: ubuntu-dev@lists.ubuntu.com
License: LGPL-3.0
Platform: UNKNOWN
Requires-Dist: urwid
